causal_tracer/__init__.py
causal_tracer/causal_tracing/AsyncTracePatchProcessor.py
causal_tracer/causal_tracing/CausalTracer.py
causal_tracer/causal_tracing/HiddenFlow.py
causal_tracer/causal_tracing/LayerConfig.py
causal_tracer/causal_tracing/guess_subject.py
causal_tracer/causal_tracing/pick_noise_level.py
causal_tracer/causal_tracing/plot_hidden_flow_heatmap.py
causal_tracer/lib/PseudoFuture.py
causal_tracer/lib/TraceLayer.py
causal_tracer/lib/TraceLayerDict.py
causal_tracer/lib/constants.py
causal_tracer/lib/layer_matching.py
causal_tracer/lib/logger.py
causal_tracer/lib/token_utils.py
causal_tracer/lib/torch_utils.py
causal_tracer/lib/util.py
causal_tracer-1.1.0.dist-info/LICENSE
causal_tracer-1.1.0.dist-info/METADATA
causal_tracer-1.1.0.dist-info/WHEEL
causal_tracer-1.1.0.dist-info/RECORD
