Metadata-Version: 2.1
Name: causal-tracer
Version: 1.1.0
Summary: 
Home-page: https://github.com/chanind/causal-tracer
Author: David Chanin
Author-email: chanindav@gmail.com
Requires-Python: >=3.10,<4.0
Classifier: Programming Language :: Python :: 3
Classifier: Programming Language :: Python :: 3.10
Classifier: Programming Language :: Python :: 3.11
Classifier: Programming Language :: Python :: 3.12
Requires-Dist: matplotlib (>=3.7.1,<4.0.0)
Requires-Dist: tqdm (>=4.66.1,<5.0.0)
Requires-Dist: transformers (>=4.28.1,<5.0.0)
Project-URL: Repository, https://github.com/chanind/causal-tracer
